.gitignore
CHANGES.txt
README.txt
setup.py
src/collective/__init__.py
src/collective.js.speakjs.egg-info/PKG-INFO
src/collective.js.speakjs.egg-info/SOURCES.txt
src/collective.js.speakjs.egg-info/dependency_links.txt
src/collective.js.speakjs.egg-info/entry_points.txt
src/collective.js.speakjs.egg-info/namespace_packages.txt
src/collective.js.speakjs.egg-info/not-zip-safe
src/collective.js.speakjs.egg-info/requires.txt
src/collective.js.speakjs.egg-info/top_level.txt
src/collective/js/__init__.py
src/collective/js/speakjs/__init__.py
src/collective/js/speakjs/configure.zcml
src/collective/js/speakjs/profiles/default/jsregistry.xml
src/collective/js/speakjs/profiles/default/metadata.xml
src/collective/js/speakjs/static/License.txt
src/collective/js/speakjs/static/speakClient.js
src/collective/js/speakjs/static/speakGenerator.js
src/collective/js/speakjs/static/speakWorker.js