Metadata-Version: 1.0
Name: collective.js.speakjs
Version: 1.0.0
Summary: Text-to-Speech in JavaScript using eSpeak
Home-page: https://github.com/collective/collective.js.speakjs/
Author: Asko Soukka
Author-email: asko.soukka@iki.fi
License: GPL3
Platform: UNKNOWN
Classifier: Programming Language :: Python
